not_in_pandas/__init__.py
not_in_pandas-0.1.1.dist-info/LICENSE.txt
not_in_pandas-0.1.1.dist-info/METADATA
not_in_pandas-0.1.1.dist-info/WHEEL
not_in_pandas-0.1.1.dist-info/top_level.txt
not_in_pandas-0.1.1.dist-info/RECORD
