Metadata-Version: 2.1
Name: not-in-pandas
Version: 0.1.1
Summary: A package that adds the notin method to pandas.Series and pandas.DataFrame objects
Home-page: https://github.com/lucas-abbate/not-in-pandas
Author: lucas-abbate
Author-email: abbatelucas@gmail.com
Classifier: Programming Language :: Python :: 3
Classifier: Operating System :: OS Independent
Requires-Python: >=3.6
License-File: LICENSE.txt
Requires-Dist: pandas (>=1.0.0)
